SQLMatches/__init__.py
SQLMatches/background_tasks.py
SQLMatches/caches.py
SQLMatches/communities.py
SQLMatches/constants.py
SQLMatches/decorators.py
SQLMatches/demos.py
SQLMatches/exceptions.py
SQLMatches/key_loader.py
SQLMatches/middlewares.py
SQLMatches/misc.py
SQLMatches/on_conflict.py
SQLMatches/resources.py
SQLMatches/responses.py
SQLMatches/settings.py
SQLMatches/tables.py
SQLMatches/version.py
SQLMatches/webhook_pusher.py
SQLMatches/community/__init__.py
SQLMatches/community/community.py
SQLMatches/community/key.py
SQLMatches/community/match.py
SQLMatches/community/models.py
SQLMatches/community/server.py
SQLMatches/maps/austria.jpg
SQLMatches/maps/cache.jpg
SQLMatches/maps/canals.jpg
SQLMatches/maps/cbble.jpg
SQLMatches/maps/dust.png
SQLMatches/maps/dust2.jpg
SQLMatches/maps/inferno.jpg
SQLMatches/maps/invalid.png
SQLMatches/maps/mirage.jpg
SQLMatches/maps/nuke.jpg
SQLMatches/maps/overpass.jpg
SQLMatches/maps/train.jpg
SQLMatches/routes/__init__.py
SQLMatches/routes/download.py
SQLMatches/routes/errors.py
SQLMatches/routes/steam.py
SQLMatches/routes/webhooks.py
SQLMatches/routes/websockets.py
SQLMatches/routes/api/admin.py
SQLMatches/routes/api/auto_setup.py
SQLMatches/routes/api/communities.py
SQLMatches/routes/api/community.py
SQLMatches/routes/api/key.py
SQLMatches/routes/api/matches.py
SQLMatches/routes/api/misc.py
SQLMatches/routes/api/players.py
SQLMatches/routes/api/profile.py
SQLMatches/routes/api/server.py
SQLMatches/routes/api/version.py
SQLMatches/stripe/__init__.py
SQLMatches/stripe/card.py
SQLMatches/stripe/customer.py
SQLMatches/stripe/models.py
SQLMatches/stripe/subscription.py
SQLMatches/templates/__init__.py
SQLMatches/templates/email.html
SQLMatches/tests/base.py
SQLMatches/tests/test_match_api.py
SQLMatches/user/__init__.py
SQLMatches/user/models.py
SQLMatches-0.3.6.dist-info/LICENSE
SQLMatches-0.3.6.dist-info/METADATA
SQLMatches-0.3.6.dist-info/WHEEL
SQLMatches-0.3.6.dist-info/top_level.txt
SQLMatches-0.3.6.dist-info/RECORD
