Metadata-Version: 2.1
Name: SQLMatches
Version: 0.3.6
Summary: SQLMatches, match & demos recorder.
Home-page: https://github.com/WardPearce/SQLMatches
Author: WardPearce
Author-email: wardpearce@protonmail.com
License: GPL v3
Platform: UNKNOWN
Requires-Python: >=3.6
Requires-Dist: starlette
Requires-Dist: asyncpg
Requires-Dist: aiomysql
Requires-Dist: aiosqlite
Requires-Dist: databases
Requires-Dist: aiofiles
Requires-Dist: itsdangerous
Requires-Dist: uvicorn
Requires-Dist: sqlalchemy
Requires-Dist: aiohttp
Requires-Dist: webargs
Requires-Dist: webargs-starlette
Requires-Dist: backblaze
Requires-Dist: marshmallow
Requires-Dist: asynctest
Requires-Dist: websockets
Requires-Dist: aiojobs
Requires-Dist: aiocache[redis]
Requires-Dist: msgpack
Requires-Dist: bcrypt (>=3.1.7)
Requires-Dist: python-socketio (==4.6.1)
Requires-Dist: validators
Requires-Dist: apispec
Requires-Dist: starlette-apispec (>=1.0.3)
Requires-Dist: cryptography
Requires-Dist: python-dotenv
Requires-Dist: aiosmtplib (>=1.1.4)
Requires-Dist: Jinja2
Requires-Dist: aioftp
